CHANGES.rst
LICENSE
MANIFEST.in
README.rst
setup.py
django_simple_open_graph.egg-info/PKG-INFO
django_simple_open_graph.egg-info/SOURCES.txt
django_simple_open_graph.egg-info/dependency_links.txt
django_simple_open_graph.egg-info/requires.txt
django_simple_open_graph.egg-info/top_level.txt
simple_open_graph/__init__.py
simple_open_graph/models.py
simple_open_graph/utils.py
simple_open_graph/templatetags/__init__.py
simple_open_graph/templatetags/simple_open_graph.py