Metadata-Version: 1.1
Name: django-simple-open-graph
Version: 0.3
Summary: Django package for simplicity embed open graph (og:) layout in templates for different objects
Home-page: https://github.com/saippuakauppias/django-simple-open-graph
Author: Denis Veselov
Author-email: progr.mail@gmail.com
License: ISC
Platform: UNKNOWN
Classifier: Development Status :: 5 - Production/Stable
Classifier: Framework :: Django
Classifier: Intended Audience :: Developers
Classifier: License :: OSI Approved :: ISC License (ISCL)
Classifier: Operating System :: OS Independent
Classifier: Programming Language :: Python
Classifier: Programming Language :: Python :: 2.6
Classifier: Programming Language :: Python :: 2.7
Classifier: Topic :: Internet :: WWW/HTTP
